ivisualizer/__init__.py
ivisualizer-0.0.1.dist-info/LICENSE
ivisualizer-0.0.1.dist-info/METADATA
ivisualizer-0.0.1.dist-info/WHEEL
ivisualizer-0.0.1.dist-info/top_level.txt
ivisualizer-0.0.1.dist-info/RECORD
